luna.py-0.1.3.dist-info/METADATA
luna.py-0.1.3.dist-info/WHEEL
luna/__init__.py
luna/__init__.pyi
luna/py.typed
luna/luna.cpython-312-x86_64-linux-gnu.so
luna.py-0.1.3.dist-info/RECORD
