Metadata-Version: 2.1
Name: luna.py
Version: 0.1.3
Classifier: Programming Language :: Rust
Classifier: Programming Language :: Python :: Implementation :: CPython
Classifier: Programming Language :: Python :: Implementation :: PyPy
Summary: Simple string templating engine for Sugari Bot written in Rust.
Requires-Python: >=3.8
